Makefile
Products.IssueDealer-configure.zcml
README.txt
setup.py
Products/__init__.py
Products.IssueDealer.egg-info/PKG-INFO
Products.IssueDealer.egg-info/SOURCES.txt
Products.IssueDealer.egg-info/dependency_links.txt
Products.IssueDealer.egg-info/entry_points.txt
Products.IssueDealer.egg-info/namespace_packages.txt
Products.IssueDealer.egg-info/not-zip-safe
Products.IssueDealer.egg-info/requires.txt
Products.IssueDealer.egg-info/top_level.txt
Products/HTMLTools/__init__.py
Products/HTMLTools/changes.txt
Products/HTMLTools/clean.sh
Products/HTMLTools/credits.txt
Products/HTMLTools/feedparser.py
Products/HTMLTools/html.py
Products/HTMLTools/license.txt
Products/HTMLTools/test.html
Products/IssueDealer/README.txt
Products/IssueDealer/__init__.py
Products/IssueDealer/base.py
Products/IssueDealer/base_browse.py
Products/IssueDealer/base_calendar.py
Products/IssueDealer/base_placement.py
Products/IssueDealer/base_publish.py
Products/IssueDealer/base_search.py
Products/IssueDealer/base_sequence.py
Products/IssueDealer/base_tree.py
Products/IssueDealer/base_utilities.py
Products/IssueDealer/changes.txt
Products/IssueDealer/config.py
Products/IssueDealer/copy_types.py
Products/IssueDealer/extensions.py
Products/IssueDealer/functional_tests
Products/IssueDealer/functions.py
Products/IssueDealer/html4css1.py
Products/IssueDealer/html4css1_inline.py
Products/IssueDealer/id_config.py
Products/IssueDealer/image.py
Products/IssueDealer/importers.py
Products/IssueDealer/install.txt
Products/IssueDealer/issue.py
Products/IssueDealer/issue_dealer.py
Products/IssueDealer/issue_dealer_catalog.py
Products/IssueDealer/issue_dealer_notifications.py
Products/IssueDealer/laf_mixin.py
Products/IssueDealer/laf_object.py
Products/IssueDealer/laf_root.py
Products/IssueDealer/license.txt
Products/IssueDealer/mixins.py
Products/IssueDealer/permissions.py
Products/IssueDealer/problems.txt
Products/IssueDealer/publisher.py
Products/IssueDealer/readme.txt
Products/IssueDealer/refresh.txt
Products/IssueDealer/relation.py
Products/IssueDealer/report.py
Products/IssueDealer/rest.py
Products/IssueDealer/session.py
Products/IssueDealer/session_folder.py
Products/IssueDealer/session_manager.py
Products/IssueDealer/test.bat
Products/IssueDealer/test.sh
Products/IssueDealer/tests.py
Products/IssueDealer/upgrade.txt
Products/IssueDealer/user.py
