Metadata-Version: 1.1
Name: Products.IssueDealer
Version: 0.9.133
Summary: The Issue Dealer is an application for managing information. It is currently used by organizations and individuals to manage day-to-day tasks and information.
Home-page: http://issuedealer.com
Author: Morten W. Petersen
Author-email: morphex@gmail.com
License: GPL
Keywords: python zope2 cms
Platform: UNKNOWN
Classifier: Programming Language :: Python
Classifier: Development Status :: 3 - Alpha
Classifier: Framework :: Zope2
Classifier: License :: OSI Approved :: GNU General Public License v2 (GPLv2)
Classifier: Natural Language :: English
Classifier: Operating System :: OS Independent
Classifier: Topic :: Internet :: WWW/HTTP
Classifier: Topic :: Software Development :: Bug Tracking
Classifier: Intended Audience :: Developers
Classifier: Intended Audience :: End Users/Desktop
